README.rst
setup.py
libnl/__init__.py
libnl/attr.py
libnl/cache.py
libnl/cache_mngt.py
libnl/errno_.py
libnl/error.py
libnl/handlers.py
libnl/list_.py
libnl/misc.py
libnl/msg.py
libnl/msg_.py
libnl/nl.py
libnl/object.py
libnl/socket_.py
libnl/types.py
libnl/utils.py
libnl.egg-info/PKG-INFO
libnl.egg-info/SOURCES.txt
libnl.egg-info/dependency_links.txt
libnl.egg-info/top_level.txt
libnl.egg-info/zip-safe
libnl/genl/__init__.py
libnl/genl/ctrl.py
libnl/genl/family.py
libnl/genl/genl.py
libnl/genl/mngt.py
libnl/linux_private/__init__.py
libnl/linux_private/genetlink.py
libnl/linux_private/if_link.py
libnl/linux_private/netlink.py
libnl/linux_private/rtnetlink.py
libnl/netlink_private/__init__.py
libnl/netlink_private/cache_api.py
libnl/netlink_private/netlink.py
libnl/netlink_private/object_api.py
libnl/netlink_private/types.py
libnl/nl80211/__init__.py
libnl/nl80211/helpers.py
libnl/nl80211/iw_scan.py
libnl/nl80211/iw_util.py
libnl/nl80211/nl80211.py