Metadata-Version: 1.1
Name: libnl
Version: 0.2.0
Summary: Pure Python port of the Netlink protocol library suite.
Home-page: https://github.com/Robpol86/libnl
Author: @Robpol86
Author-email: robpol86@gmail.com
License: LGPL2.1
Keywords: netlink libnl libnl-genl nl80211
Platform: UNKNOWN
Classifier: Development Status :: 4 - Beta
Classifier: Intended Audience :: Developers
Classifier: License :: OSI Approved :: GNU Lesser General Public License v2 or later (LGPLv2+)
Classifier: Operating System :: POSIX :: Linux
Classifier: Programming Language :: Python :: 2.6
Classifier: Programming Language :: Python :: 2.7
Classifier: Programming Language :: Python :: 3.3
Classifier: Programming Language :: Python :: 3.4
Classifier: Programming Language :: Python :: Implementation :: PyPy
Classifier: Topic :: Software Development :: Libraries
Classifier: Topic :: System :: Networking
Classifier: Topic :: System :: Operating System Kernels :: Linux
